tbd_calver_versioning.py
tbd_calver_versioning-2025.2.26.2.data/data/bin/README.md
tbd_calver_versioning-2025.2.26.2.data/data/bin/determine_tbd_calver_version_number.sh
tbd_calver_versioning-2025.2.26.2.data/data/bin/tag_repo_with_version_number.sh
tbd_calver_versioning-2025.2.26.2.data/data/repo_inspection/README.md
tbd_calver_versioning-2025.2.26.2.data/data/repo_inspection/checkout_git_repo_properly.sh
tbd_calver_versioning-2025.2.26.2.data/data/repo_inspection/configure_credential_helper.sh
tbd_calver_versioning-2025.2.26.2.data/data/repo_inspection/determine_commit_where_branch_created.sh
tbd_calver_versioning-2025.2.26.2.data/data/repo_inspection/determine_if_changed_files_match_triggers.sh
tbd_calver_versioning-2025.2.26.2.data/data/repo_inspection/determine_if_commit_is_merge_commit.sh
tbd_calver_versioning-2025.2.26.2.data/data/repo_inspection/get_changed_files_on_branch.sh
tbd_calver_versioning-2025.2.26.2.data/data/repo_inspection/get_changed_files_since_commit.sh
tbd_calver_versioning-2025.2.26.2.dist-info/METADATA
tbd_calver_versioning-2025.2.26.2.dist-info/WHEEL
tbd_calver_versioning-2025.2.26.2.dist-info/top_level.txt
tbd_calver_versioning-2025.2.26.2.dist-info/RECORD
