Metadata-Version: 2.2
Name: tbd-calver-versioning
Version: 2025.2.26.2
Summary: A set of tools to manage a code repository using trunk based development and CalVer.
Home-page: https://github.com/taylor-schneider/tbd-calver-versioning
Author: tschneider
Author-email: tschneider@live.com
Classifier: Programming Language :: Unix Shell
Classifier: Programming Language :: Python :: 3
Classifier: License :: OSI Approved :: GNU Lesser General Public License v3 (LGPLv3)
Classifier: Operating System :: OS Independent
Requires-Dist: ShellUtilities==2.1.12
Dynamic: author
Dynamic: author-email
Dynamic: classifier
Dynamic: description
Dynamic: description-content-type
Dynamic: home-page
Dynamic: requires-dist
Dynamic: summary
